triton_bert/__init__.py
triton_bert/model/bge_m3.py
triton_bert/model/model_4_triton.py
triton_bert/tests/__init__.py
triton_bert/tests/dataset/medical_qa.jsonl
triton_bert/tests/test_bge_m3.py
triton_bert/tests/test_biencoder.py
triton_bert/tests/test_chitchat.py
triton_bert/tests/test_crossencoder.py
triton_bert/tests/test_generate_bgem3_triton_model.py
triton_bert/tests/test_generate_triton_bert.py
triton_bert/tests/test_generate_triton_model.py
triton_bert/tests/test_intention_classification.py
triton_bert/tests/test_mrc.py
triton_bert/tests/test_pgvector_triton.py
triton_bert/tests/test_triton_bert.py
triton_bert/tests/vocab/bert_agent_intention_classification/README.txt
triton_bert/tests/vocab/bert_agent_intention_classification/class.txt
triton_bert/tests/vocab/bert_agent_intention_classification/config.json
triton_bert/tests/vocab/bert_agent_intention_classification/vocab.txt
triton_bert/tests/vocab/bert_customer_intention_classification/README.txt
triton_bert/tests/vocab/bert_customer_intention_classification/class.txt
triton_bert/tests/vocab/bert_customer_intention_classification/config.json
triton_bert/tests/vocab/bert_customer_intention_classification/vocab.txt
triton_bert/tests/vocab/bert_mrc/config.json
triton_bert/tests/vocab/bert_mrc/vocab.txt
triton_bert/triton_bert.py
triton_bert/vector_db/pgvector_triton.py
triton_bert-0.3.3.dist-info/LICENSE
triton_bert-0.3.3.dist-info/METADATA
triton_bert-0.3.3.dist-info/WHEEL
triton_bert-0.3.3.dist-info/RECORD
