Metadata-Version: 2.1
Name: triton-bert
Version: 0.3.3
Summary: easy to use bert with nvidia triton inference server
License: MIT
Author: yyw794
Author-email: yyw794@126.com
Requires-Python: >=3.8,<4.0
Classifier: License :: OSI Approved :: MIT License
Classifier: Programming Language :: Python :: 3
Classifier: Programming Language :: Python :: 3.8
Classifier: Programming Language :: Python :: 3.9
Classifier: Programming Language :: Python :: 3.10
Classifier: Programming Language :: Python :: 3.11
Classifier: Programming Language :: Python :: 3.12
Requires-Dist: jsonlines (>=4.0.0,<5.0.0)
Requires-Dist: more-itertools (>=10.1.0,<11.0.0)
Requires-Dist: onnx (>=1.15.0,<2.0.0)
Requires-Dist: pgvector (>=0.2.4,<0.3.0)
Requires-Dist: protobuf (>=4.23,<5.0)
Requires-Dist: psycopg2-binary (>=2.9.9,<3.0.0)
Requires-Dist: sqlmodel (>=0.0.14,<0.0.15)
Requires-Dist: transformers (>=4.36.2,<5.0.0)
Requires-Dist: tritonclient[grpc,http] (>=2.41.0,<3.0.0)
